.gitignore
LICENSE.md
MANIFEST.in
README.rst
setup.py
docs/Makefile
docs/blah.txt
docs/generate-autodoc.sh
docs/libgs.db
docs/make.bat
docs/make_html.sh
docs/requirements-doc.txt
docs/source/conf.py
docs/source/console_scripts.rst
docs/source/index.rst
docs/source/_static/placeholder.txt
docs/source/_templates/placeholder.txt
docs/source/_templates/autosummary/class.rst
docs/source/_templates/autosummary/module.rst
src/libgs/__init__.py
src/libgs/console_scripts.py
src/libgs/database.py
src/libgs/emulators.py
src/libgs/groundstation.py
src/libgs/hardware.py
src/libgs/monitoring.py
src/libgs/propagator.py
src/libgs/restapi.py
src/libgs/rpc.py
src/libgs/scheduler.py
src/libgs/utils.py
src/libgs/visualisation.py
src/libgs.egg-info/PKG-INFO
src/libgs.egg-info/SOURCES.txt
src/libgs.egg-info/dependency_links.txt
src/libgs.egg-info/entry_points.txt
src/libgs.egg-info/not-zip-safe
src/libgs.egg-info/requires.txt
src/libgs.egg-info/top_level.txt
src/libgs/protocols/__init__.py
src/libgs/protocols/protocolbase.py
tests/requirements-test.txt
tests/run_test.sh
tests/integration-tests/test_all.py
tests/unit-tests/test_database.py
tests/unit-tests/test_restapi.py
tests/unit-tests/test_scheduler.py