Metadata-Version: 1.1
Name: libgs
Version: 1.2.1
Summary: Ground station operation library
Home-page: UNKNOWN
Author: Kjetil Wormnes / University of New South Wales
Author-email: kjetil@wormnes.com
License: UNKNOWN
Keywords: satellite spacecraft operations ground station predict
Platform: UNKNOWN
Classifier: Development Status :: 3 - Alpha
Classifier: Intended Audience :: Science/Research
Classifier: Topic :: Scientific/Engineering :: Astronomy
Classifier: Topic :: Software Development :: Build Tools
Classifier: Topic :: System :: Hardware :: Hardware Drivers
Classifier: License :: OSI Approved :: MIT License
Classifier: Programming Language :: Python :: 2.7
